Workbook

Sheet Assumptions
B2: Product Line and Prices | H2: Assumtions
B3: Name | C3: Description | D3: Price (EUR/month)* | E3: Sale mix (by units) | F3: Comment | H3: Metric | I3: Value | J3: Comment | K3: Justification
B4: Lens | C4: Real time edge vision for inventory awareness | D4: 2000 | E4: 0.35 | F4: Cheap, deployed everywhere | H4: Sales and Customer Acqusition
B5: Robotic Picking | C5: Autonomous picking across thousands of SKUs | D5: 6000 | E5: 0.3 | F5: core product that every wharehouse needs | H5: Cost per lead | I5: 500 | J5: Advertisement costs need to generate one lead. In more complecated models it is pssible to reduce this number as time goes and the company gets more traction | K5: Enterprise robotics buyers are a narrow audience of warehouse/logistics operators, requiring targeted LinkedIn, trade show, and industry media spend => CPL is naturally high compared to consumer or SMB SaaS.
B6: Putwall Automation | C6: Automated sortation for batch picking and returns | D6: 4000 | E6: 0.15 | F6: only needed in large ops | H6: Leads Generation growth rate (monthly) | I6: 0.04 | J6: % by which leads generation growth as adds start working | K6: As ad campaigns mature and brand awareness builds, each euro of ad spend generates progressively more inbound
B7: Humanoid (Cortex) | C7: AI human like dexterity. Pickingm sorting, and packaging | D7: 8000 | E7: 0.15 | F7: common but secondary | H7: Conversion rate | I7: 0.02 | J7: % of lead enterprises that are converted into clients | K7: Enterprise automation deals require extensive POC, ROI validation and multi-stakeholder sign-off, making 2% realistic
B8: Return Handling | C8: Autimated inspection and sorting of returns | D8: 3000 | E8: 0.05 | F8: early and experimental | H8: Churn (monthly) | I8: 0.01 | J8: Churn rate of enterprises cancelling contracts. When an enterprise cancells a contract it cancells all robots that it owns | K8: Robotic picking is deeply embedded in warehouse operations, ripping it out has high switching costs.
B9: Installation cost | C9: One time cost for installing a robot | D9: 1000 | H9: Initial robots per customer | I9: 15 | J9: When a new enterprise is aquired it receives this amount of robots from the beginning | K9: Enterprise warehouses typically automate multiple picking stations simultaneously at go-live rather than a single pilot unit, given integration costs and ROI only becomes compelling at meaningful scale.
H10: Robots expansion rate (monthly) | I10: 0.11 | J10: Existing enterprise clients purchase and install new robots every month | K10: Once a client has live robots and sees ROI, adding incremental stations is low-friction.
B11: *Price assumtions are based on the estimates from https://robotomated.com/learn/cost/warehouse-robot-cost-guide | H11: Average revenue per Robot | I11: =SUMPRODUCT(Assumptions!D4:D8,Assumptions!E4:E8) -> 4450 | J11: Average cost of one robot based on price and sale mix
H12: Cost of Goods Sold
H13: Deployments/ engeneers/ month | I13: 8 | J13: The amount of robots one engeneer can deploy a month.Since the amount of deployments vary across months we do not fire and hire them every month but retain those from previous month + add new if required | K13: A single deployment engineer can install, configure and validate roughly 2 robots per week. Physical commissioning, WMS integration and operator training requires time per station.
C14: - an assumption, changing it changes the inputs of the financial model | H14: Enterprises/ customer support/ month | I14: 2 | J14: The amount of client enterprises one customer support representatice can handle | K14: Enterprise clients require high-touch account management, especially in the first months post-deployment
C15: - formula. Should not be changed | H15: Salary (engeneer) (monthly) | I15: 5000 | J15: Base monthly salary of an engeneer deploying robots | K15: Competitive monthly gross salary for a robotics/software deployment engineer
H16: Salary (customer support) (monthly) | I16: 3500 | J16: Base monthly salary of a customer support agent | K16: Slightly below engineering given less technical depth required
H17: Enterprises/ technical support/ month | I17: 2 | J17: The amount of client enterprises one technical support team member can handle | K17: Technical support agents handle live production incidents and remote robot interventions. Each enterprise can generate multiple simultaneous alerts, especially early post-deployment, capping capacity at ~2 accounts per agent.
H18: Salary (technical support) (monthly) | I18: 5000 | J18: Base monthly salary of a technical support tream member | K18: On par with deployment engineers: requires deep Cortex platform knowledge and ability to diagnose real-time robotics failures remotely under time pressure.
H19: Cloud/ Compute infrastructure (per robot) | I19: 500 | J19: Cost of AI models, databases, etc. Initially we have 0 robots but we still have to pay for the cloud compute to keep the infrastructure ready | K19: Covers edge GPU amortisation; cloud inference and model update syncing; telemetry and image log storage; and remote monitoring/observability tooling
H20: Operative Expenses
H21: Rent | I21: 10000 | J21: Office rent costs per month | K21: Office space for a ~40–50 person team, including a physical robot test lab
H22: Office and administration | I22: 5000 | J22: Administrative costs per month | K22: Covers consumables, IT infrastructure, internal software licences (CRM, ERP, communication tools), insurance and miscellaneous overhead
H23: Leads/ Sales agent / month | I23: 5 | J23: Leads that one sales agent can contact a month | K23: Enterprise outreach involves deep research, personalised outreach and multi-touch follow-up => 5 qualified conversations per agent per month is realistic for cold outbound into senior logistics and operations decision-makers.
H24: Sales agents salary (monthly) | I24: 4000 | J24: Base monthly salary for the sales representative | K24: Base salary component for a mid-market enterprise
H25: Commisiion per new robot | I25: 0.1 | J25: Commission that a sales person gets per one robot installed | K25: Performance-based incentive on each robot installed
H26: Initial RnD team | I26: 10 | J26: AI/ML engeneers; software engeneers; I assume a constunt number, in more complicated models it is possible to grow the team through time | K26: Core team of AI/ML researchers, robotics software engineers and computer vision specialists needed to maintain and advance the Cortex VLAM. Below 10 the model development and deployment pipeline stalls.
H27: RnD team salary | I27: 8000 | J27: Base monthly salary for the RnD team | K27: Reflects the competitive salary required to attract and retain AI/ML engineers
H28: Executive and Leadership | I28: 5 | J28: CEO, CTO, CFO, VPs; I assume a constunt number, in more complicated models it is possible to grow the team through time | K28: CEO, CTO, CFO and two VPs (Sales, Engineering)
H29: Executive and Leadership salary (monthly) | I29: 12000 | J29: Leadership monthly salaries | K29: Reflects senior leadership compensation in a well-funded German deep-tech startup
H30: Other personel | I30: 6 | J30: Finance, Accounting, HR, Project managers; I assume a constunt number, in more complicated models it is possible to grow the team through time | K30: Finance, accounting, HR, legal liaison and project management
H31: Other personel monthly salary | I31: 5000 | J31: Other Personel monthly salary | K31: Blended average across finance, HR and ops profiles
H32: Other Assumptions
H33: Effective tax rate | I33: 0.3 | J33: Applicable tax rate on profit | K33: Federal+state tax

Sheet PnL
B2: All cells in this tbale are based on formulas or links and are dimamic and aouto-updated
B4: Month | C4: M1 | D4: M2 | E4: M3 | F4: M4 | G4: M5 | H4: M6 | I4: M7 | J4: M8 | K4: M9 | L4: M10 | M4: M11 | N4: M12 | O4: M13 | P4: M14 | Q4: M15 | R4: M16 | S4: M17 | T4: M18 | U4: M19 | V4: M20 | W4: M21 | X4: M22 | Y4: M23 | Z4: M24 | AA4: M25 | AB4: M26 | AC4: M27 | AD4: M28 | AE4: M29 | AF4: M30 | AG4: M31 | AH4: M32 | AI4: M33 | AJ4: M34 | AK4: M35 | AL4: M36
B6: Active Robots | C6: ='Sales and Customer Acquisition '!C13 -> 0 | D6: ='Sales and Customer Acquisition '!D13 -> 0 | E6: ='Sales and Customer Acquisition '!E13 -> 0 | F6: ='Sales and Customer Acquisition '!F13 -> 0 | G6: ='Sales and Customer Acquisition '!G13 -> 0 | H6: ='Sales and Customer Acquisition '!H13 -> 0 | I6: ='Sales and Customer Acquisition '!I13 -> 0 | J6: ='Sales and Customer Acquisition '!J13 -> 0 | ... AL6: ='Sales and Customer Acquisition '!AL13 -> 395
B7: Active Enterprise Customers | C7: ='Sales and Customer Acquisition '!C9 -> 0 | D7: ='Sales and Customer Acquisition '!D9 -> 0 | E7: ='Sales and Customer Acquisition '!E9 -> 0 | F7: ='Sales and Customer Acquisition '!F9 -> 0 | G7: ='Sales and Customer Acquisition '!G9 -> 0 | H7: ='Sales and Customer Acquisition '!H9 -> 0 | I7: ='Sales and Customer Acquisition '!I9 -> 0 | J7: ='Sales and Customer Acquisition '!J9 -> 0 | ... AL7: ='Sales and Customer Acquisition '!AL9 -> 6
B9: Revenue | C9: =SUM(C11:C12) -> 0 | D9: =SUM(D11:D12) -> 0 | E9: =SUM(E11:E12) -> 0 | F9: =SUM(F11:F12) -> 0 | G9: =SUM(G11:G12) -> 0 | H9: =SUM(H11:H12) -> 0 | I9: =SUM(I11:I12) -> 0 | J9: =SUM(J11:J12) -> 0 | ... AL9: =SUM(AL11:AL12) -> 1796750
B11: Subscription revenue | C11: ='Sales and Customer Acquisition '!C20 -> 0 | D11: ='Sales and Customer Acquisition '!D20 -> 0 | E11: ='Sales and Customer Acquisition '!E20 -> 0 | F11: ='Sales and Customer Acquisition '!F20 -> 0 | G11: ='Sales and Customer Acquisition '!G20 -> 0 | H11: ='Sales and Customer Acquisition '!H20 -> 0 | I11: ='Sales and Customer Acquisition '!I20 -> 0 | J11: ='Sales and Customer Acquisition '!J20 -> 0 | ... AL11: ='Sales and Customer Acquisition '!AL20 -> 1757750
B12: Installation revenue | C12: ='Sales and Customer Acquisition '!C21 -> 0 | D12: ='Sales and Customer Acquisition '!D21 -> 0 | E12: ='Sales and Customer Acquisition '!E21 -> 0 | F12: ='Sales and Customer Acquisition '!F21 -> 0 | G12: ='Sales and Customer Acquisition '!G21 -> 0 | H12: ='Sales and Customer Acquisition '!H21 -> 0 | I12: ='Sales and Customer Acquisition '!I21 -> 0 | J12: ='Sales and Customer Acquisition '!J21 -> 0 | ... AL12: ='Sales and Customer Acquisition '!AL21 -> 39000
B14: Cost of Goods Sold | C14: =SUM(C16:C20) -> 18500 | D14: =SUM(D16:D20) -> 18500 | E14: =SUM(E16:E20) -> 18500 | F14: =SUM(F16:F20) -> 18500 | G14: =SUM(G16:G20) -> 18500 | H14: =SUM(H16:H20) -> 18500 | I14: =SUM(I16:I20) -> 18500 | J14: =SUM(J16:J20) -> 18500 | ... AL14: =SUM(AL16:AL20) -> 253000
B16: Cloud/ Compute infrastructure | C16: =COGS!C10 -> 5000 | D16: =COGS!D10 -> 5000 | E16: =COGS!E10 -> 5000 | F16: =COGS!F10 -> 5000 | G16: =COGS!G10 -> 5000 | H16: =COGS!H10 -> 5000 | I16: =COGS!I10 -> 5000 | J16: =COGS!J10 -> 5000 | ... AL16: =COGS!AL10 -> 197500
B18: Deployment Engeneers | C18: =COGS!C13 -> 5000 | D18: =COGS!D13 -> 5000 | E18: =COGS!E13 -> 5000 | F18: =COGS!F13 -> 5000 | G18: =COGS!G13 -> 5000 | H18: =COGS!H13 -> 5000 | I18: =COGS!I13 -> 5000 | J18: =COGS!J13 -> 5000 | ... AL18: =COGS!AL13 -> 30000
B19: Customer Support | C19: =COGS!C16 -> 3500 | D19: =COGS!D16 -> 3500 | E19: =COGS!E16 -> 3500 | F19: =COGS!F16 -> 3500 | G19: =COGS!G16 -> 3500 | H19: =COGS!H16 -> 3500 | I19: =COGS!I16 -> 3500 | J19: =COGS!J16 -> 3500 | ... AL19: =COGS!AL16 -> 10500
B20: Technical Support | C20: =COGS!C19 -> 5000 | D20: =COGS!D19 -> 5000 | E20: =COGS!E19 -> 5000 | F20: =COGS!F19 -> 5000 | G20: =COGS!G19 -> 5000 | H20: =COGS!H19 -> 5000 | I20: =COGS!I19 -> 5000 | J20: =COGS!J19 -> 5000 | ... AL20: =COGS!AL19 -> 15000
B22: Operating Expenses | C22: =C24+C25+C27+C33 -> 189000 | D22: =D24+D25+D27+D33 -> 189000 | E22: =E24+E25+E27+E33 -> 191500 | F22: =F24+F25+F27+F33 -> 195600 | G22: =G24+G25+G27+G33 -> 195704 | H22: =H24+H25+H27+H33 -> 195812.16 | I22: =I24+I25+I27+I33 -> 195924.65 | J22: =J24+J25+J27+J33 -> 196041.63 | ... AL22: =AL24+AL25+AL27+AL33 -> 227475.95
B24: Rent | C24: =OpEx!C6 -> 10000 | D24: =OpEx!D6 -> 10000 | E24: =OpEx!E6 -> 10000 | F24: =OpEx!F6 -> 10000 | G24: =OpEx!G6 -> 10000 | H24: =OpEx!H6 -> 10000 | I24: =OpEx!I6 -> 10000 | J24: =OpEx!J6 -> 10000 | ... AL24: =OpEx!AL6 -> 10000
B25: Office and Administration | C25: =OpEx!C7 -> 5000 | D25: =OpEx!D7 -> 5000 | E25: =OpEx!E7 -> 5000 | F25: =OpEx!F7 -> 5000 | G25: =OpEx!G7 -> 5000 | H25: =OpEx!H7 -> 5000 | I25: =OpEx!I7 -> 5000 | J25: =OpEx!J7 -> 5000 | ... AL25: =OpEx!AL7 -> 5000
B27: Salaries | C27: =SUM(C28:C31) -> 174000 | D27: =SUM(D28:D31) -> 174000 | E27: =SUM(E28:E31) -> 174000 | F27: =SUM(F28:F31) -> 178000 | G27: =SUM(G28:G31) -> 178000 | H27: =SUM(H28:H31) -> 178000 | I27: =SUM(I28:I31) -> 178000 | J27: =SUM(J28:J31) -> 178000 | ... AL27: =SUM(AL28:AL31) -> 203355
B28: Sales team | C28: =OpEx!C10 -> 4000 | D28: =OpEx!D10 -> 4000 | E28: =OpEx!E10 -> 4000 | F28: =OpEx!F10 -> 8000 | G28: =OpEx!G10 -> 8000 | H28: =OpEx!H10 -> 8000 | I28: =OpEx!I10 -> 8000 | J28: =OpEx!J10 -> 8000 | ... AL28: =OpEx!AL10 -> 33355
B29: RnD team | C29: =OpEx!C15 -> 80000 | D29: =OpEx!D15 -> 80000 | E29: =OpEx!E15 -> 80000 | F29: =OpEx!F15 -> 80000 | G29: =OpEx!G15 -> 80000 | H29: =OpEx!H15 -> 80000 | I29: =OpEx!I15 -> 80000 | J29: =OpEx!J15 -> 80000 | ... AL29: =OpEx!AL15 -> 80000
B30: Leadership | C30: =OpEx!C16 -> 60000 | D30: =OpEx!D16 -> 60000 | E30: =OpEx!E16 -> 60000 | F30: =OpEx!F16 -> 60000 | G30: =OpEx!G16 -> 60000 | H30: =OpEx!H16 -> 60000 | I30: =OpEx!I16 -> 60000 | J30: =OpEx!J16 -> 60000 | ... AL30: =OpEx!AL16 -> 60000
B31: Other Personel | C31: =OpEx!C17 -> 30000 | D31: =OpEx!D17 -> 30000 | E31: =OpEx!E17 -> 30000 | F31: =OpEx!F17 -> 30000 | G31: =OpEx!G17 -> 30000 | H31: =OpEx!H17 -> 30000 | I31: =OpEx!I17 -> 30000 | J31: =OpEx!J17 -> 30000 | ... AL31: =OpEx!AL17 -> 30000
B33: Advertisement | C33: =OpEx!C9 -> 0 | D33: =OpEx!D9 -> 0 | E33: =OpEx!E9 -> 2500 | F33: =OpEx!F9 -> 2600 | G33: =OpEx!G9 -> 2704 | H33: =OpEx!H9 -> 2812.16 | I33: =OpEx!I9 -> 2924.6464 | J33: =OpEx!J9 -> 3041.6323 | ... AL33: =OpEx!AL9 -> 9120.9527
B35: EBITDA | C35: =C9-C14-C22 -> -207500 | D35: =D9-D14-D22 -> -207500 | E35: =E9-E14-E22 -> -210000 | F35: =F9-F14-F22 -> -214100 | G35: =G9-G14-G22 -> -214204 | H35: =H9-H14-H22 -> -214312.16 | I35: =I9-I14-I22 -> -214424.65 | J35: =J9-J14-J22 -> -214541.63 | ... AL35: =AL9-AL14-AL22 -> 1316274
B37: Taxes | C37: =MAX(C35*Assumptions!$I$33,0) -> 0 | D37: =MAX(D35*Assumptions!$I$33,0) -> 0 | E37: =MAX(E35*Assumptions!$I$33,0) -> 0 | F37: =MAX(F35*Assumptions!$I$33,0) -> 0 | G37: =MAX(G35*Assumptions!$I$33,0) -> 0 | H37: =MAX(H35*Assumptions!$I$33,0) -> 0 | I37: =MAX(I35*Assumptions!$I$33,0) -> 0 | J37: =MAX(J35*Assumptions!$I$33,0) -> 0 | ... AL37: =MAX(AL35*Assumptions!$I$33,0) -> 394882.21
B39: NET INCOME | C39: =C35-C37 -> -207500 | D39: =D35-D37 -> -207500 | E39: =E35-E37 -> -210000 | F39: =F35-F37 -> -214100 | G39: =G35-G37 -> -214204 | H39: =H35-H37 -> -214312.16 | I39: =I35-I37 -> -214424.65 | J39: =J35-J37 -> -214541.63 | ... AL39: =AL35-AL37 -> 921391.83
B41: Profit Margin | C41: =IFERROR(C39/C9,0) -> 0 | D41: =IFERROR(D39/D9,0) -> 0 | E41: =IFERROR(E39/E9,0) -> 0 | F41: =IFERROR(F39/F9,0) -> 0 | G41: =IFERROR(G39/G9,0) -> 0 | H41: =IFERROR(H39/H9,0) -> 0 | I41: =IFERROR(I39/I9,0) -> 0 | J41: =IFERROR(J39/J9,0) -> 0 | ... AL41: =IFERROR(AL39/AL9,0) -> 0.51281026
B42: MRR | C42: ='Sales and Customer Acquisition '!C24 -> 0 | D42: ='Sales and Customer Acquisition '!D24 -> 0 | E42: ='Sales and Customer Acquisition '!E24 -> 0 | F42: ='Sales and Customer Acquisition '!F24 -> 0 | G42: ='Sales and Customer Acquisition '!G24 -> 0 | H42: ='Sales and Customer Acquisition '!H24 -> 0 | I42: ='Sales and Customer Acquisition '!I24 -> 0 | J42: ='Sales and Customer Acquisition '!J24 -> 0 | ... AL42: ='Sales and Customer Acquisition '!AL24 -> 1584200
B43: New MRR | C43: =Assumptions!$I$11*'Sales and Customer Acquisition '!C15 -> 0 | D43: =Assumptions!$I$11*'Sales and Customer Acquisition '!D15 -> 0 | E43: =Assumptions!$I$11*'Sales and Customer Acquisition '!E15 -> 0 | F43: =Assumptions!$I$11*'Sales and Customer Acquisition '!F15 -> 0 | G43: =Assumptions!$I$11*'Sales and Customer Acquisition '!G15 -> 0 | H43: =Assumptions!$I$11*'Sales and Customer Acquisition '!H15 -> 0 | I43: =Assumptions!$I$11*'Sales and Customer Acquisition '!I15 -> 0 | J43: =Assumptions!$I$11*'Sales and Customer Acquisition '!J15 -> 0 | ... AL43: =Assumptions!$I$11*'Sales and Customer Acquisition '!AL15 -> 173550
B44: Expansion MRR | C44: =Assumptions!$I$11*'Sales and Customer Acquisition '!C17 -> 0 | D44: =Assumptions!$I$11*'Sales and Customer Acquisition '!D17 -> 0 | E44: =Assumptions!$I$11*'Sales and Customer Acquisition '!E17 -> 0 | F44: =Assumptions!$I$11*'Sales and Customer Acquisition '!F17 -> 0 | G44: =Assumptions!$I$11*'Sales and Customer Acquisition '!G17 -> 0 | H44: =Assumptions!$I$11*'Sales and Customer Acquisition '!H17 -> 0 | I44: =Assumptions!$I$11*'Sales and Customer Acquisition '!I17 -> 0 | J44: =Assumptions!$I$11*'Sales and Customer Acquisition '!J17 -> 0 | ... AL44: =Assumptions!$I$11*'Sales and Customer Acquisition '!AL17 -> 173550
B45: Robot acquisition cost | C45: =IFERROR((C33+C28)/C6,0) -> 0 | D45: =IFERROR((D33+D28)/D6,0) -> 0 | E45: =IFERROR((E33+E28)/E6,0) -> 0 | F45: =IFERROR((F33+F28)/F6,0) -> 0 | G45: =IFERROR((G33+G28)/G6,0) -> 0 | H45: =IFERROR((H33+H28)/H6,0) -> 0 | I45: =IFERROR((I33+I28)/I6,0) -> 0 | J45: =IFERROR((J33+J28)/J6,0) -> 0 | ... AL45: =IFERROR((AL33+AL28)/AL6,0) -> 107.53406

Sheet Sales and Customer Acquisition 
C2: - manual imputs for assumptions; the rest is based on formulas and is auto-updated
B4: Month | C4: M1 | D4: M2 | E4: M3 | F4: M4 | G4: M5 | H4: M6 | I4: M7 | J4: M8 | K4: M9 | L4: M10 | M4: M11 | N4: M12 | O4: M13 | P4: M14 | Q4: M15 | R4: M16 | S4: M17 | T4: M18 | U4: M19 | V4: M20 | W4: M21 | X4: M22 | Y4: M23 | Z4: M24 | AA4: M25 | AB4: M26 | AC4: M27 | AD4: M28 | AE4: M29 | AF4: M30 | AG4: M31 | AH4: M32 | AI4: M33 | AJ4: M34 | AK4: M35 | AL4: M36
B6: Leads Generated | C6: 0 | D6: 0 | E6: 5 | F6: =E6*(1+Assumptions!$I$6) -> 5.2 | G6: =F6*(1+Assumptions!$I$6) -> 5.408 | H6: =G6*(1+Assumptions!$I$6) -> 5.62432 | I6: =H6*(1+Assumptions!$I$6) -> 5.8492928 | J6: =I6*(1+Assumptions!$I$6) -> 6.0832645 | K6: =J6*(1+Assumptions!$I$6) -> 6.3265951 | L6: =K6*(1+Assumptions!$I$6) -> 6.5796589 | M6: =L6*(1+Assumptions!$I$6) -> 6.8428453 | ... AL6: =AK6*(1+Assumptions!$I$6) -> 18.241905
B7: Cummulative # leads | C7: =IFERROR(B7+C6,0) -> 0 | D7: =IFERROR(C7+D6,0) -> 0 | E7: =IFERROR(D7+E6,0) -> 5 | F7: =IFERROR(E7+F6,0) -> 10.2 | G7: =IFERROR(F7+G6,0) -> 15.608 | H7: =IFERROR(G7+H6,0) -> 21.23232 | I7: =IFERROR(H7+I6,0) -> 27.081613 | J7: =IFERROR(I7+J6,0) -> 33.164877 | ... AL7: =IFERROR(AK7+AL6,0) -> 349.28954
B9: Active Enterprises | C9: =IFERROR(B9+C10-C11,0) -> 0 | D9: =IFERROR(C9+D10-D11,0) -> 0 | E9: =IFERROR(D9+E10-E11,0) -> 0 | F9: =IFERROR(E9+F10-F11,0) -> 0 | G9: =IFERROR(F9+G10-G11,0) -> 0 | H9: =IFERROR(G9+H10-H11,0) -> 0 | I9: =IFERROR(H9+I10-I11,0) -> 0 | J9: =IFERROR(I9+J10-J11,0) -> 0 | ... AL9: =IFERROR(AK9+AL10-AL11,0) -> 6
B10: New enterprises | C10: =IFERROR(ROUNDDOWN(C7*(Assumptions!$I$7),0) -ROUNDDOWN('Sales and Customer Acquisition '!B7*(Assumptions!$I$7),0),0) -> 0 | D10: =IFERROR(ROUNDDOWN(D7*(Assumptions!$I$7),0) -ROUNDDOWN('Sales and Customer Acquisition '!C7*(Assumptions!$I$7),0),0) -> 0 | E10: =IFERROR(ROUNDDOWN(E7*(Assumptions!$I$7),0) -ROUNDDOWN('Sales and Customer Acquisition '!D7*(Assumptions!$I$7),0),0) -> 0 | F10: =IFERROR(ROUNDDOWN(F7*(Assumptions!$I$7),0) -ROUNDDOWN('Sales and Customer Acquisition '!E7*(Assumptions!$I$7),0),0) -> 0 | G10: =IFERROR(ROUNDDOWN(G7*(Assumptions!$I$7),0) -ROUNDDOWN('Sales and Customer Acquisition '!F7*(Assumptions!$I$7),0),0) -> 0 | H10: =IFERROR(ROUNDDOWN(H7*(Assumptions!$I$7),0) -ROUNDDOWN('Sales and Customer Acquisition '!G7*(Assumptions!$I$7),0),0) -> 0 | I10: =IFERROR(ROUNDDOWN(I7*(Assumptions!$I$7),0) -ROUNDDOWN('Sales and Customer Acquisition '!H7*(Assumptions!$I$7),0),0) -> 0 | J10: =IFERROR(ROUNDDOWN(J7*(Assumptions!$I$7),0) -ROUNDDOWN('Sales and Customer Acquisition '!I7*(Assumptions!$I$7),0),0) -> 0 | ... AL10: =IFERROR(ROUNDDOWN(AL7*(Assumptions!$I$7),0) -ROUNDDOWN('Sales and Customer Acquisition '!AK7*(Assumptions!$I$7),0),0) -> 0
B11: Churned enetrprises | C11: =IFERROR(ROUNDDOWN(B9*Assumptions!$I$8,0),0) -> 0 | D11: =IFERROR(ROUNDDOWN(C9*Assumptions!$I$8,0),0) -> 0 | E11: =IFERROR(ROUNDDOWN(D9*Assumptions!$I$8,0),0) -> 0 | F11: =IFERROR(ROUNDDOWN(E9*Assumptions!$I$8,0),0) -> 0 | G11: =IFERROR(ROUNDDOWN(F9*Assumptions!$I$8,0),0) -> 0 | H11: =IFERROR(ROUNDDOWN(G9*Assumptions!$I$8,0),0) -> 0 | I11: =IFERROR(ROUNDDOWN(H9*Assumptions!$I$8,0),0) -> 0 | J11: =IFERROR(ROUNDDOWN(I9*Assumptions!$I$8,0),0) -> 0 | ... AL11: =IFERROR(ROUNDDOWN(AK9*Assumptions!$I$8,0),0) -> 0
B13: Active robots | C13: =IFERROR(B13+C15-C14,0) -> 0 | D13: =IFERROR(C13+D15-D14,0) -> 0 | E13: =IFERROR(D13+E15-E14,0) -> 0 | F13: =IFERROR(E13+F15-F14,0) -> 0 | G13: =IFERROR(F13+G15-G14,0) -> 0 | H13: =IFERROR(G13+H15-H14,0) -> 0 | I13: =IFERROR(H13+I15-I14,0) -> 0 | J13: =IFERROR(I13+J15-J14,0) -> 0 | ... AL13: =IFERROR(AK13+AL15-AL14,0) -> 395
B14: Churned robots | C14: =IFERROR(C11*ROUND(B13/B9,0),0) -> 0 | D14: =IFERROR(D11*ROUND(C13/C9,0),0) -> 0 | E14: =IFERROR(E11*ROUND(D13/D9,0),0) -> 0 | F14: =IFERROR(F11*ROUND(E13/E9,0),0) -> 0 | G14: =IFERROR(G11*ROUND(F13/F9,0),0) -> 0 | H14: =IFERROR(H11*ROUND(G13/G9,0),0) -> 0 | I14: =IFERROR(I11*ROUND(H13/H9,0),0) -> 0 | J14: =IFERROR(J11*ROUND(I13/I9,0),0) -> 0 | ... AL14: =IFERROR(AL11*ROUND(AK13/AK9,0),0) -> 0
B15: Total New robots | C15: =SUM(C16:C17) -> 0 | D15: =SUM(D16:D17) -> 0 | E15: =SUM(E16:E17) -> 0 | F15: =SUM(F16:F17) -> 0 | G15: =SUM(G16:G17) -> 0 | H15: =SUM(H16:H17) -> 0 | I15: =SUM(I16:I17) -> 0 | J15: =SUM(J16:J17) -> 0 | ... AL15: =SUM(AL16:AL17) -> 39
B16: New enterprise installments | C16: =C10*Assumptions!$I$9 -> 0 | D16: =D10*Assumptions!$I$9 -> 0 | E16: =E10*Assumptions!$I$9 -> 0 | F16: =F10*Assumptions!$I$9 -> 0 | G16: =G10*Assumptions!$I$9 -> 0 | H16: =H10*Assumptions!$I$9 -> 0 | I16: =I10*Assumptions!$I$9 -> 0 | J16: =J10*Assumptions!$I$9 -> 0 | ... AL16: =AL10*Assumptions!$I$9 -> 0
B17: Expansion installments | C17: =IFERROR(ROUNDDOWN(B13*(Assumptions!$I$10+1)-B13,0),0) -> 0 | D17: =IFERROR(ROUNDDOWN(C13*(Assumptions!$I$10+1)-C13,0),0) -> 0 | E17: =IFERROR(ROUNDDOWN(D13*(Assumptions!$I$10+1)-D13,0),0) -> 0 | F17: =IFERROR(ROUNDDOWN(E13*(Assumptions!$I$10+1)-E13,0),0) -> 0 | G17: =IFERROR(ROUNDDOWN(F13*(Assumptions!$I$10+1)-F13,0),0) -> 0 | H17: =IFERROR(ROUNDDOWN(G13*(Assumptions!$I$10+1)-G13,0),0) -> 0 | I17: =IFERROR(ROUNDDOWN(H13*(Assumptions!$I$10+1)-H13,0),0) -> 0 | J17: =IFERROR(ROUNDDOWN(I13*(Assumptions!$I$10+1)-I13,0),0) -> 0 | ... AL17: =IFERROR(ROUNDDOWN(AK13*(Assumptions!$I$10+1)-AK13,0),0) -> 39
B19: Total Revenue | C19: =C20+C21 -> 0 | D19: =D20+D21 -> 0 | E19: =E20+E21 -> 0 | F19: =F20+F21 -> 0 | G19: =G20+G21 -> 0 | H19: =H20+H21 -> 0 | I19: =I20+I21 -> 0 | J19: =J20+J21 -> 0 | ... AL19: =AL20+AL21 -> 1796750
B20: Subscription revenue | C20: ='Sales and Customer Acquisition '!C13*Assumptions!$I$11 -> 0 | D20: ='Sales and Customer Acquisition '!D13*Assumptions!$I$11 -> 0 | E20: ='Sales and Customer Acquisition '!E13*Assumptions!$I$11 -> 0 | F20: ='Sales and Customer Acquisition '!F13*Assumptions!$I$11 -> 0 | G20: ='Sales and Customer Acquisition '!G13*Assumptions!$I$11 -> 0 | H20: ='Sales and Customer Acquisition '!H13*Assumptions!$I$11 -> 0 | I20: ='Sales and Customer Acquisition '!I13*Assumptions!$I$11 -> 0 | J20: ='Sales and Customer Acquisition '!J13*Assumptions!$I$11 -> 0 | ... AL20: ='Sales and Customer Acquisition '!AL13*Assumptions!$I$11 -> 1757750
B21: Installments revenue | C21: =C15*Assumptions!$D$9 -> 0 | D21: =D15*Assumptions!$D$9 -> 0 | E21: =E15*Assumptions!$D$9 -> 0 | F21: =F15*Assumptions!$D$9 -> 0 | G21: =G15*Assumptions!$D$9 -> 0 | H21: =H15*Assumptions!$D$9 -> 0 | I21: =I15*Assumptions!$D$9 -> 0 | J21: =J15*Assumptions!$D$9 -> 0 | ... AL21: =AL15*Assumptions!$D$9 -> 39000
B23: New bookings | C23: =C15*Assumptions!$I$11 -> 0 | D23: =D15*Assumptions!$I$11 -> 0 | E23: =E15*Assumptions!$I$11 -> 0 | F23: =F15*Assumptions!$I$11 -> 0 | G23: =G15*Assumptions!$I$11 -> 0 | H23: =H15*Assumptions!$I$11 -> 0 | I23: =I15*Assumptions!$I$11 -> 0 | J23: =J15*Assumptions!$I$11 -> 0 | ... AL23: =AL15*Assumptions!$I$11 -> 173550
B24: Reacurring revenue | C24: =C25*Assumptions!$I$11 -> 0 | D24: =D25*Assumptions!$I$11 -> 0 | E24: =E25*Assumptions!$I$11 -> 0 | F24: =F25*Assumptions!$I$11 -> 0 | G24: =G25*Assumptions!$I$11 -> 0 | H24: =H25*Assumptions!$I$11 -> 0 | I24: =I25*Assumptions!$I$11 -> 0 | J24: =J25*Assumptions!$I$11 -> 0 | ... AL24: =AL25*Assumptions!$I$11 -> 1584200
B25: Reacurring robots | C25: =IFERROR(B13-C14,0) -> 0 | D25: =IFERROR(C13-D14,0) -> 0 | E25: =IFERROR(D13-E14,0) -> 0 | F25: =IFERROR(E13-F14,0) -> 0 | G25: =IFERROR(F13-G14,0) -> 0 | H25: =IFERROR(G13-H14,0) -> 0 | I25: =IFERROR(H13-I14,0) -> 0 | J25: =IFERROR(I13-J14,0) -> 0 | ... AL25: =IFERROR(AK13-AL14,0) -> 356

Sheet COGS
B2: All cells here are based on formulas and are auto-updated depending on assumptions
B4: Month | C4: M1 | D4: M2 | E4: M3 | F4: M4 | G4: M5 | H4: M6 | I4: M7 | J4: M8 | K4: M9 | L4: M10 | M4: M11 | N4: M12 | O4: M13 | P4: M14 | Q4: M15 | R4: M16 | S4: M17 | T4: M18 | U4: M19 | V4: M20 | W4: M21 | X4: M22 | Y4: M23 | Z4: M24 | AA4: M25 | AB4: M26 | AC4: M27 | AD4: M28 | AE4: M29 | AF4: M30 | AG4: M31 | AH4: M32 | AI4: M33 | AJ4: M34 | AK4: M35 | AL4: M36
B6: Active enerprises | C6: ='Sales and Customer Acquisition '!C9 -> 0 | D6: ='Sales and Customer Acquisition '!D9 -> 0 | E6: ='Sales and Customer Acquisition '!E9 -> 0 | F6: ='Sales and Customer Acquisition '!F9 -> 0 | G6: ='Sales and Customer Acquisition '!G9 -> 0 | H6: ='Sales and Customer Acquisition '!H9 -> 0 | I6: ='Sales and Customer Acquisition '!I9 -> 0 | J6: ='Sales and Customer Acquisition '!J9 -> 0 | ... AL6: ='Sales and Customer Acquisition '!AL9 -> 6
B7: Active robots | C7: ='Sales and Customer Acquisition '!C13 -> 0 | D7: ='Sales and Customer Acquisition '!D13 -> 0 | E7: ='Sales and Customer Acquisition '!E13 -> 0 | F7: ='Sales and Customer Acquisition '!F13 -> 0 | G7: ='Sales and Customer Acquisition '!G13 -> 0 | H7: ='Sales and Customer Acquisition '!H13 -> 0 | I7: ='Sales and Customer Acquisition '!I13 -> 0 | J7: ='Sales and Customer Acquisition '!J13 -> 0 | ... AL7: ='Sales and Customer Acquisition '!AL13 -> 395
B8: New robots | C8: ='Sales and Customer Acquisition '!C15 -> 0 | D8: ='Sales and Customer Acquisition '!D15 -> 0 | E8: ='Sales and Customer Acquisition '!E15 -> 0 | F8: ='Sales and Customer Acquisition '!F15 -> 0 | G8: ='Sales and Customer Acquisition '!G15 -> 0 | H8: ='Sales and Customer Acquisition '!H15 -> 0 | I8: ='Sales and Customer Acquisition '!I15 -> 0 | J8: ='Sales and Customer Acquisition '!J15 -> 0 | ... AL8: ='Sales and Customer Acquisition '!AL15 -> 39
B10: Cloud/ Compute infrastructure | C10: =MAX(5000, C7*Assumptions!$I$19) -> 5000 | D10: =MAX(5000, D7*Assumptions!$I$19) -> 5000 | E10: =MAX(5000, E7*Assumptions!$I$19) -> 5000 | F10: =MAX(5000, F7*Assumptions!$I$19) -> 5000 | G10: =MAX(5000, G7*Assumptions!$I$19) -> 5000 | H10: =MAX(5000, H7*Assumptions!$I$19) -> 5000 | I10: =MAX(5000, I7*Assumptions!$I$19) -> 5000 | J10: =MAX(5000, J7*Assumptions!$I$19) -> 5000 | ... AL10: =MAX(5000, AL7*Assumptions!$I$19) -> 197500
B12: Deployment engeneers required | C12: =MAX(ROUNDUP(COGS!C8/Assumptions!$I$13,0),B12,1) -> 1 | D12: =MAX(ROUNDUP(COGS!D8/Assumptions!$I$13,0),C12,1) -> 1 | E12: =MAX(ROUNDUP(COGS!E8/Assumptions!$I$13,0),D12,1) -> 1 | F12: =MAX(ROUNDUP(COGS!F8/Assumptions!$I$13,0),E12,1) -> 1 | G12: =MAX(ROUNDUP(COGS!G8/Assumptions!$I$13,0),F12,1) -> 1 | H12: =MAX(ROUNDUP(COGS!H8/Assumptions!$I$13,0),G12,1) -> 1 | I12: =MAX(ROUNDUP(COGS!I8/Assumptions!$I$13,0),H12,1) -> 1 | J12: =MAX(ROUNDUP(COGS!J8/Assumptions!$I$13,0),I12,1) -> 1 | ... AL12: =MAX(ROUNDUP(COGS!AL8/Assumptions!$I$13,0),AK12,1) -> 6
B13: Deployment engeneers salaries | C13: =C12*Assumptions!$I$15 -> 5000 | D13: =D12*Assumptions!$I$15 -> 5000 | E13: =E12*Assumptions!$I$15 -> 5000 | F13: =F12*Assumptions!$I$15 -> 5000 | G13: =G12*Assumptions!$I$15 -> 5000 | H13: =H12*Assumptions!$I$15 -> 5000 | I13: =I12*Assumptions!$I$15 -> 5000 | J13: =J12*Assumptions!$I$15 -> 5000 | ... AL13: =AL12*Assumptions!$I$15 -> 30000
B15: Cutomer support team required | C15: =MAX(ROUNDUP(C6/Assumptions!$I$14,0),COGS!B15,1) -> 1 | D15: =MAX(ROUNDUP(D6/Assumptions!$I$14,0),COGS!C15,1) -> 1 | E15: =MAX(ROUNDUP(E6/Assumptions!$I$14,0),COGS!D15,1) -> 1 | F15: =MAX(ROUNDUP(F6/Assumptions!$I$14,0),COGS!E15,1) -> 1 | G15: =MAX(ROUNDUP(G6/Assumptions!$I$14,0),COGS!F15,1) -> 1 | H15: =MAX(ROUNDUP(H6/Assumptions!$I$14,0),COGS!G15,1) -> 1 | I15: =MAX(ROUNDUP(I6/Assumptions!$I$14,0),COGS!H15,1) -> 1 | J15: =MAX(ROUNDUP(J6/Assumptions!$I$14,0),COGS!I15,1) -> 1 | ... AL15: =MAX(ROUNDUP(AL6/Assumptions!$I$14,0),COGS!AK15,1) -> 3
B16: Cutomer support team salary | C16: =C15*Assumptions!$I$16 -> 3500 | D16: =D15*Assumptions!$I$16 -> 3500 | E16: =E15*Assumptions!$I$16 -> 3500 | F16: =F15*Assumptions!$I$16 -> 3500 | G16: =G15*Assumptions!$I$16 -> 3500 | H16: =H15*Assumptions!$I$16 -> 3500 | I16: =I15*Assumptions!$I$16 -> 3500 | J16: =J15*Assumptions!$I$16 -> 3500 | ... AL16: =AL15*Assumptions!$I$16 -> 10500
B18: Technical support team required | C18: =MAX(ROUNDUP(C6/Assumptions!$I$17,0),COGS!B18,1) -> 1 | D18: =MAX(ROUNDUP(D6/Assumptions!$I$17,0),COGS!C18,1) -> 1 | E18: =MAX(ROUNDUP(E6/Assumptions!$I$17,0),COGS!D18,1) -> 1 | F18: =MAX(ROUNDUP(F6/Assumptions!$I$17,0),COGS!E18,1) -> 1 | G18: =MAX(ROUNDUP(G6/Assumptions!$I$17,0),COGS!F18,1) -> 1 | H18: =MAX(ROUNDUP(H6/Assumptions!$I$17,0),COGS!G18,1) -> 1 | I18: =MAX(ROUNDUP(I6/Assumptions!$I$17,0),COGS!H18,1) -> 1 | J18: =MAX(ROUNDUP(J6/Assumptions!$I$17,0),COGS!I18,1) -> 1 | ... AL18: =MAX(ROUNDUP(AL6/Assumptions!$I$17,0),COGS!AK18,1) -> 3
B19: Technical support team salary | C19: =C18*Assumptions!$I$18 -> 5000 | D19: =D18*Assumptions!$I$18 -> 5000 | E19: =E18*Assumptions!$I$18 -> 5000 | F19: =F18*Assumptions!$I$18 -> 5000 | G19: =G18*Assumptions!$I$18 -> 5000 | H19: =H18*Assumptions!$I$18 -> 5000 | I19: =I18*Assumptions!$I$18 -> 5000 | J19: =J18*Assumptions!$I$18 -> 5000 | ... AL19: =AL18*Assumptions!$I$18 -> 15000

Sheet OpEx
B2: All cells here are based on formulas and are auto-updated depending on assumptions
B4: Month | C4: M1 | D4: M2 | E4: M3 | F4: M4 | G4: M5 | H4: M6 | I4: M7 | J4: M8 | K4: M9 | L4: M10 | M4: M11 | N4: M12 | O4: M13 | P4: M14 | Q4: M15 | R4: M16 | S4: M17 | T4: M18 | U4: M19 | V4: M20 | W4: M21 | X4: M22 | Y4: M23 | Z4: M24 | AA4: M25 | AB4: M26 | AC4: M27 | AD4: M28 | AE4: M29 | AF4: M30 | AG4: M31 | AH4: M32 | AI4: M33 | AJ4: M34 | AK4: M35 | AL4: M36
B6: Rent | C6: =Assumptions!$I$21 -> 10000 | D6: =Assumptions!$I$21 -> 10000 | E6: =Assumptions!$I$21 -> 10000 | F6: =Assumptions!$I$21 -> 10000 | G6: =Assumptions!$I$21 -> 10000 | H6: =Assumptions!$I$21 -> 10000 | I6: =Assumptions!$I$21 -> 10000 | J6: =Assumptions!$I$21 -> 10000 | ... AL6: =Assumptions!$I$21 -> 10000
B7: Office and administration | C7: =Assumptions!$I$22 -> 5000 | D7: =Assumptions!$I$22 -> 5000 | E7: =Assumptions!$I$22 -> 5000 | F7: =Assumptions!$I$22 -> 5000 | G7: =Assumptions!$I$22 -> 5000 | H7: =Assumptions!$I$22 -> 5000 | I7: =Assumptions!$I$22 -> 5000 | J7: =Assumptions!$I$22 -> 5000 | ... AL7: =Assumptions!$I$22 -> 5000
B9: Lead Costs (Advertising) | C9: ='Sales and Customer Acquisition '!C6*Assumptions!$I$5 -> 0 | D9: ='Sales and Customer Acquisition '!D6*Assumptions!$I$5 -> 0 | E9: ='Sales and Customer Acquisition '!E6*Assumptions!$I$5 -> 2500 | F9: ='Sales and Customer Acquisition '!F6*Assumptions!$I$5 -> 2600 | G9: ='Sales and Customer Acquisition '!G6*Assumptions!$I$5 -> 2704 | H9: ='Sales and Customer Acquisition '!H6*Assumptions!$I$5 -> 2812.16 | I9: ='Sales and Customer Acquisition '!I6*Assumptions!$I$5 -> 2924.6464 | J9: ='Sales and Customer Acquisition '!J6*Assumptions!$I$5 -> 3041.6323 | ... AL9: ='Sales and Customer Acquisition '!AL6*Assumptions!$I$5 -> 9120.9527
B10: Sales Agents Salary | C10: =C12+C13 -> 4000 | D10: =D12+D13 -> 4000 | E10: =E12+E13 -> 4000 | F10: =F12+F13 -> 8000 | G10: =G12+G13 -> 8000 | H10: =H12+H13 -> 8000 | I10: =I12+I13 -> 8000 | J10: =J12+J13 -> 8000 | ... AL10: =AL12+AL13 -> 33355
B11: Sales agents required | C11: =MAX(1, ROUNDUP('Sales and Customer Acquisition '!C6/Assumptions!$I$23,0)) -> 1 | D11: =MAX(1, ROUNDUP('Sales and Customer Acquisition '!D6/Assumptions!$I$23,0)) -> 1 | E11: =MAX(1, ROUNDUP('Sales and Customer Acquisition '!E6/Assumptions!$I$23,0)) -> 1 | F11: =MAX(1, ROUNDUP('Sales and Customer Acquisition '!F6/Assumptions!$I$23,0)) -> 2 | G11: =MAX(1, ROUNDUP('Sales and Customer Acquisition '!G6/Assumptions!$I$23,0)) -> 2 | H11: =MAX(1, ROUNDUP('Sales and Customer Acquisition '!H6/Assumptions!$I$23,0)) -> 2 | I11: =MAX(1, ROUNDUP('Sales and Customer Acquisition '!I6/Assumptions!$I$23,0)) -> 2 | J11: =MAX(1, ROUNDUP('Sales and Customer Acquisition '!J6/Assumptions!$I$23,0)) -> 2 | ... AL11: =MAX(1, ROUNDUP('Sales and Customer Acquisition '!AL6/Assumptions!$I$23,0)) -> 4
B12: Base salary | C12: =C11*Assumptions!$I$24 -> 4000 | D12: =D11*Assumptions!$I$24 -> 4000 | E12: =E11*Assumptions!$I$24 -> 4000 | F12: =F11*Assumptions!$I$24 -> 8000 | G12: =G11*Assumptions!$I$24 -> 8000 | H12: =H11*Assumptions!$I$24 -> 8000 | I12: =I11*Assumptions!$I$24 -> 8000 | J12: =J11*Assumptions!$I$24 -> 8000 | ... AL12: =AL11*Assumptions!$I$24 -> 16000
B13: Comission | C13: ='Sales and Customer Acquisition '!C23*Assumptions!$I$25 -> 0 | D13: ='Sales and Customer Acquisition '!D23*Assumptions!$I$25 -> 0 | E13: ='Sales and Customer Acquisition '!E23*Assumptions!$I$25 -> 0 | F13: ='Sales and Customer Acquisition '!F23*Assumptions!$I$25 -> 0 | G13: ='Sales and Customer Acquisition '!G23*Assumptions!$I$25 -> 0 | H13: ='Sales and Customer Acquisition '!H23*Assumptions!$I$25 -> 0 | I13: ='Sales and Customer Acquisition '!I23*Assumptions!$I$25 -> 0 | J13: ='Sales and Customer Acquisition '!J23*Assumptions!$I$25 -> 0 | ... AL13: ='Sales and Customer Acquisition '!AL23*Assumptions!$I$25 -> 17355
B15: RnD Team Salaries | C15: =Assumptions!$I$27*Assumptions!$I$26 -> 80000 | D15: =Assumptions!$I$27*Assumptions!$I$26 -> 80000 | E15: =Assumptions!$I$27*Assumptions!$I$26 -> 80000 | F15: =Assumptions!$I$27*Assumptions!$I$26 -> 80000 | G15: =Assumptions!$I$27*Assumptions!$I$26 -> 80000 | H15: =Assumptions!$I$27*Assumptions!$I$26 -> 80000 | I15: =Assumptions!$I$27*Assumptions!$I$26 -> 80000 | J15: =Assumptions!$I$27*Assumptions!$I$26 -> 80000 | ... AL15: =Assumptions!$I$27*Assumptions!$I$26 -> 80000
B16: Executive and leadership Salaries | C16: =Assumptions!$I$28*Assumptions!$I$29 -> 60000 | D16: =Assumptions!$I$28*Assumptions!$I$29 -> 60000 | E16: =Assumptions!$I$28*Assumptions!$I$29 -> 60000 | F16: =Assumptions!$I$28*Assumptions!$I$29 -> 60000 | G16: =Assumptions!$I$28*Assumptions!$I$29 -> 60000 | H16: =Assumptions!$I$28*Assumptions!$I$29 -> 60000 | I16: =Assumptions!$I$28*Assumptions!$I$29 -> 60000 | J16: =Assumptions!$I$28*Assumptions!$I$29 -> 60000 | ... AL16: =Assumptions!$I$28*Assumptions!$I$29 -> 60000
B17: Other Personel Salaries | C17: =Assumptions!$I$30*Assumptions!$I$31 -> 30000 | D17: =Assumptions!$I$30*Assumptions!$I$31 -> 30000 | E17: =Assumptions!$I$30*Assumptions!$I$31 -> 30000 | F17: =Assumptions!$I$30*Assumptions!$I$31 -> 30000 | G17: =Assumptions!$I$30*Assumptions!$I$31 -> 30000 | H17: =Assumptions!$I$30*Assumptions!$I$31 -> 30000 | I17: =Assumptions!$I$30*Assumptions!$I$31 -> 30000 | J17: =Assumptions!$I$30*Assumptions!$I$31 -> 30000 | ... AL17: =Assumptions!$I$30*Assumptions!$I$31 -> 30000
